md_dlp/__init__.py
md_dlp/main.py
md_dlp-0.2.3.dist-info/METADATA
md_dlp-0.2.3.dist-info/WHEEL
md_dlp-0.2.3.dist-info/entry_points.txt
md_dlp-0.2.3.dist-info/top_level.txt
md_dlp-0.2.3.dist-info/RECORD
