Metadata-Version: 2.2
Name: md-dlp
Version: 0.2.3
Summary: A tool for markdown data loss prevention
Home-page: https://github.com/markshawn2020/md-dlp
Author: MarkShawn
Author-email: shawninjuly@gmail.com
Classifier: Programming Language :: Python :: 3
Classifier: License :: OSI Approved :: MIT License
Classifier: Operating System :: OS Independent
Requires-Python: >=3.6
Requires-Dist: requests>=2.25.1
Dynamic: author
Dynamic: author-email
Dynamic: classifier
Dynamic: description
Dynamic: description-content-type
Dynamic: home-page
Dynamic: requires-dist
Dynamic: requires-python
Dynamic: summary
